README.txt
setup.cfg
setup.py
docs/HISTORY.txt
docs/INSTALL.txt
docs/LICENSE.GPL
docs/LICENSE.txt
easyshop/__init__.py
easyshop.catalog.egg-info/PKG-INFO
easyshop.catalog.egg-info/SOURCES.txt
easyshop.catalog.egg-info/dependency_links.txt
easyshop.catalog.egg-info/entry_points.txt
easyshop.catalog.egg-info/namespace_packages.txt
easyshop.catalog.egg-info/not-zip-safe
easyshop.catalog.egg-info/requires.txt
easyshop.catalog.egg-info/top_level.txt
easyshop/catalog/__init__.py
easyshop/catalog/configure.zcml
easyshop/catalog/profiles.zcml
easyshop/catalog/tests.py
easyshop/catalog/adapters/__init__.py
easyshop/catalog/adapters/category_management.py
easyshop/catalog/adapters/configure.zcml
easyshop/catalog/adapters/data.py
easyshop/catalog/adapters/formats.py
easyshop/catalog/adapters/group_management.py
easyshop/catalog/adapters/prices.py
easyshop/catalog/adapters/product_management.py
easyshop/catalog/adapters/product_variants_management.py
easyshop/catalog/adapters/property_management.py
easyshop/catalog/adapters/taxes.py
easyshop/catalog/ajax/__init__.py
easyshop/catalog/ajax/configure.zcml
easyshop/catalog/ajax/properties.py
easyshop/catalog/browser/__init__.py
easyshop/catalog/browser/add_to_cart.py
easyshop/catalog/browser/category_categories_view.pt
easyshop/catalog/browser/category_products_view.pt
easyshop/catalog/browser/configure.zcml
easyshop/catalog/browser/easyshop_macros.py
easyshop/catalog/browser/manage_categories_view.pt
easyshop/catalog/browser/manage_categories_view.py
easyshop/catalog/browser/manage_products_view.pt
easyshop/catalog/browser/manage_products_view.py
easyshop/catalog/browser/manage_properties_view.pt
easyshop/catalog/browser/manage_properties_view.py
easyshop/catalog/browser/manage_variants_view.pt
easyshop/catalog/browser/manage_variants_view.py
easyshop/catalog/browser/product_selector_view.pt
easyshop/catalog/browser/product_view.pt
easyshop/catalog/browser/product_view.py
easyshop/catalog/browser/product_zoom_view.pt
easyshop/catalog/browser/product_zoom_view.py
easyshop/catalog/content/__init__.py
easyshop/catalog/content/category.py
easyshop/catalog/content/containers.py
easyshop/catalog/content/easyshop_image.py
easyshop/catalog/content/product.py
easyshop/catalog/content/product_property.py
easyshop/catalog/content/product_property_option.py
